[
  {
    "id": "orion",
    "name": "Orion",
    "lines": [
      [[5.9195, 7.407], [5.2423, -8.2016]],
      [[5.2423, -8.2016], [5.4189, -2.3971]],
      [[5.4189, -2.3971], [5.6036, -1.2019]],
      [[5.6036, -1.2019], [5.6793, -1.9426]],
      [[5.6793, -1.9426], [5.5906, -5.9099]],
      [[5.5906, -5.9099], [5.5334, -0.2991]],
      [[5.5334, -0.2991], [5.9195, 7.407]]
    ]
  },
  {
    "id": "ursa-major",
    "name": "Ursa Major",
    "lines": [
      [[11.0621, 61.7508], [11.0307, 56.3824]],
      [[11.0307, 56.3824], [11.8972, 53.6948]],
      [[11.8972, 53.6948], [12.2571, 57.0326]],
      [[12.2571, 57.0326], [12.9005, 55.9598]],
      [[12.9005, 55.9598], [13.3987, 54.9254]],
      [[13.3987, 54.9254], [13.7923, 49.3133]]
    ]
  },
  {
    "id": "cassiopeia",
    "name": "Cassiopeia",
    "lines": [
      [[0.6751, 56.5374], [1.4303, 60.2353]],
      [[1.4303, 60.2353], [0.1529, 59.1498]],
      [[0.1529, 59.1498], [23.0794, 60.9647]],
      [[23.0794, 60.9647], [23.9766, 58.7701]]
    ]
  },
  {
    "id": "cygnus",
    "name": "Cygnus",
    "lines": [
      [[20.6905, 45.280], [20.3705, 40.2567]],
      [[20.3705, 40.2567], [19.512, 27.9597]],
      [[20.3705, 40.2567], [21.2467, 38.0443]],
      [[20.3705, 40.2567], [19.7496, 45.1304]]
    ]
  },
  {
    "id": "lyra",
    "name": "Lyra",
    "lines": [
      [[18.6156, 38.7837], [18.7462, 37.6051]],
      [[18.7462, 37.6051], [18.8347, 33.3627]],
      [[18.8347, 33.3627], [18.9821, 32.6896]],
      [[18.9821, 32.6896], [18.7462, 37.6051]]
    ]
  },
  {
    "id": "scorpius",
    "name": "Scorpius",
    "lines": [
      [[16.4901, -26.432], [16.8645, -38.047]],
      [[16.8645, -38.047], [17.5601, -37.1038]],
      [[17.5601, -37.1038], [17.7081, -39.0299]],
      [[17.7081, -39.0299], [17.7931, -40.1269]]
    ]
  },
  {
    "id": "taurus",
    "name": "Taurus",
    "lines": [
      [[4.5986, 16.509], [4.4769, 15.8709]],
      [[4.4769, 15.8709], [4.3299, 15.6277]],
      [[4.3299, 15.6277], [4.0526, 14.8449]],
      [[4.0526, 14.8449], [4.0526, 14.8449]]
    ]
  },
  {
    "id": "leo",
    "name": "Leo",
    "lines": [
      [[10.1395, 11.967], [10.3329, 19.8415]],
      [[10.3329, 19.8415], [11.2351, 20.5237]],
      [[11.2351, 20.5237], [11.8176, 14.5719]],
      [[11.8176, 14.5719], [10.1395, 11.967]]
    ]
  },
  {
    "id": "gemini",
    "name": "Gemini",
    "lines": [
      [[7.5767, 31.888], [7.7554, 28.026]],
      [[7.5767, 31.888], [6.6285, 16.399]],
      [[7.7554, 28.026], [6.6285, 16.399]]
    ]
  },
  {
    "id": "pegasus",
    "name": "Pegasus",
    "lines": [
      [[23.0794, 15.2053], [23.0629, 28.0828]],
      [[23.0629, 28.0828], [0.1398, 29.0904]],
      [[0.1398, 29.0904], [0.2206, 15.1836]],
      [[0.2206, 15.1836], [23.0794, 15.2053]]
    ]
  },
  {
    "id": "andromeda",
    "name": "Andromeda",
    "lines": [
      [[0.1398, 29.0904], [1.1622, 35.6206]],
      [[1.1622, 35.6206], [2.0649, 42.3297]]
    ]
  },
  {
    "id": "crux",
    "name": "Crux",
    "lines": [
      [[12.4433, -63.0991], [12.7953, -59.6888]],
      [[12.7953, -59.6888], [12.5194, -57.1132]],
      [[12.5194, -57.1132], [12.2524, -58.7489]]
    ]
  },
  {
    "id": "sagittarius",
    "name": "Sagittarius",
    "lines": [
      [[18.4029, -34.3847], [18.3499, -29.8281]],
      [[18.3499, -29.8281], [18.4662, -25.4216]],
      [[18.4662, -25.4216], [18.9211, -26.2967]],
      [[18.9211, -26.2967], [19.0435, -29.8801]]
    ]
  },
  {
    "id": "aquarius",
    "name": "Aquarius",
    "lines": [
      [[22.0964, -0.3199], [21.5250, -5.5711]],
      [[21.5250, -5.5711], [21.6682, -9.0152]],
      [[21.6682, -9.0152], [22.9108, -15.8208]]
    ]
  },
  {
    "id": "perseus",
    "name": "Perseus",
    "lines": [
      [[3.4054, 49.8612], [3.1361, 40.9556]]
    ]
  },
  {
    "id": "canis-major",
    "name": "Canis Major",
    "lines": [
      [[6.7525, -16.716], [6.9769, -28.972]]
    ]
  }
]
